{"staro":{"all":1772,"hard":1636,"clay":1753,"grass":1494,"n":275},"kessl":{"all":1848,"hard":1841,"clay":1590,"grass":1672,"n":289},"navar":{"all":1893,"hard":1720,"clay":1821,"grass":1784,"n":304},"lys":{"all":1797,"hard":1802,"clay":1705,"grass":1500,"n":279},"towns":{"all":1851,"hard":1839,"clay":1734,"grass":1505,"n":295},"mcnal":{"all":1861,"hard":1720,"clay":1796,"grass":1702,"n":293},"osaka":{"all":2079,"hard":1941,"clay":1919,"grass":1854,"n":290},"pegul":{"all":2160,"hard":2128,"clay":1939,"grass":1904,"n":329},"li":{"all":1779,"hard":1728,"clay":1720,"grass":1415,"n":296},"kenin":{"all":1712,"hard":1656,"clay":1737,"grass":1533,"n":297},"tomlj":{"all":1772,"hard":1773,"clay":1590,"grass":1688,"n":281},"putin":{"all":1805,"hard":1796,"clay":1781,"grass":1513,"n":308},"sinia":{"all":1894,"hard":1866,"clay":1701,"grass":1681,"n":292},"boult":{"all":1809,"hard":1800,"clay":1679,"grass":1698,"n":291},"svito":{"all":2080,"hard":2008,"clay":2109,"grass":1710,"n":302},"anisi":{"all":2061,"hard":2032,"clay":1808,"grass":1843,"n":286},"plisk":{"all":1878,"hard":1776,"clay":1760,"grass":1701,"n":295},"sakka":{"all":1827,"hard":1822,"clay":1752,"grass":1604,"n":304},"kasat":{"all":1817,"hard":1776,"clay":1844,"grass":1574,"n":307},"raduc":{"all":1898,"hard":1840,"clay":1720,"grass":1790,"n":236},"oliyn":{"all":1760,"hard":1532,"clay":1800,"grass":1369,"n":289},"siege":{"all":1786,"hard":1700,"clay":1725,"grass":1641,"n":296},"kalin1":{"all":1850,"hard":1654,"clay":1926,"grass":1546,"n":289},"crist":{"all":1847,"hard":1814,"clay":1760,"grass":1369,"n":298},"zhang":{"all":1742,"hard":1736,"clay":1540,"grass":1606,"n":293},"keys":{"all":2050,"hard":1973,"clay":1967,"grass":1864,"n":292},"mucho":{"all":2116,"hard":2090,"clay":1869,"grass":1861,"n":285},"tjen":{"all":1722,"hard":1826,"clay":1669,"grass":1445,"n":180},"chwal":{"all":1868,"hard":1707,"clay":1897,"grass":1414,"n":291},"krejc":{"all":1956,"hard":1913,"clay":1683,"grass":1858,"n":288},"blink":{"all":1713,"hard":1641,"clay":1609,"grass":1620,"n":307},"linet":{"all":1790,"hard":1721,"clay":1740,"grass":1622,"n":297},"paoli":{"all":1917,"hard":1867,"clay":1944,"grass":1773,"n":312},"yastr":{"all":1817,"hard":1739,"clay":1800,"grass":1642,"n":293},"ostap":{"all":1921,"hard":1793,"clay":1850,"grass":1842,"n":294},"sabal":{"all":2299,"hard":2335,"clay":2134,"grass":1930,"n":325},"vidma":{"all":1673,"hard":1719,"clay":1603,"grass":1556,"n":215},"maria":{"all":1810,"hard":1515,"clay":1534,"grass":1816,"n":307},"potap":{"all":1937,"hard":1731,"clay":1983,"grass":1580,"n":291},"bouzk":{"all":1902,"hard":1795,"clay":1803,"grass":1774,"n":292},"vekic":{"all":1803,"hard":1695,"clay":1752,"grass":1730,"n":299},"samso":{"all":1832,"hard":1748,"clay":1784,"grass":1768,"n":300},"jones":{"all":1660,"hard":1659,"clay":1747,"grass":1371,"n":272},"merte":{"all":1958,"hard":1895,"clay":1829,"grass":1813,"n":305},"benci":{"all":2076,"hard":2023,"clay":1930,"grass":1821,"n":296},"gauff":{"all":2157,"hard":2106,"clay":2112,"grass":1717,"n":323},"serra":{"all":1827,"hard":1831,"clay":1729,"grass":1521,"n":285},"bapti":{"all":1900,"hard":1828,"clay":1821,"grass":1586,"n":291},"golub":{"all":1771,"hard":1666,"clay":1698,"grass":1608,"n":305},"swiat":{"all":2138,"hard":2091,"clay":2135,"grass":1931,"n":336},"kosty":{"all":2118,"hard":1978,"clay":2061,"grass":1693,"n":297},"cirst":{"all":2028,"hard":1978,"clay":1913,"grass":1522,"n":294},"zaraz":{"all":1653,"hard":1656,"clay":1580,"grass":1506,"n":304},"cocci":{"all":1813,"hard":1790,"clay":1731,"grass":1686,"n":300},"stear":{"all":1820,"hard":1751,"clay":1837,"grass":1400,"n":295},"birre":{"all":1788,"hard":1796,"clay":1447,"grass":1550,"n":297},"parks":{"all":1661,"hard":1679,"clay":1604,"grass":1445,"n":302},"alexa":{"all":1852,"hard":1809,"clay":1716,"grass":1744,"n":306},"kawa":{"all":1662,"hard":1374,"clay":1738,"grass":1551,"n":296},"tarar":{"all":1709,"hard":1761,"clay":1474,"grass":1473,"n":276},"ruse":{"all":1857,"hard":1714,"clay":1733,"grass":1771,"n":295},"rybak":{"all":2194,"hard":2264,"clay":2045,"grass":1793,"n":311},"frech":{"all":1676,"hard":1703,"clay":1621,"grass":1422,"n":303},"kuder1":{"all":1874,"hard":1793,"clay":1757,"grass":1651,"n":301},"karta":{"all":1898,"hard":1867,"clay":1655,"grass":1671,"n":235},"grach":{"all":1791,"hard":1738,"clay":1676,"grass":1590,"n":302},"kalin":{"all":1954,"hard":1928,"clay":1830,"grass":1672,"n":276},"galfi":{"all":1631,"hard":1600,"clay":1738,"grass":1507,"n":290},"zakha":{"all":1714,"hard":1758,"clay":1520,"grass":1542,"n":299},"wang1":{"all":1799,"hard":1793,"clay":1736,"grass":1541,"n":292},"bonda":{"all":1790,"hard":1614,"clay":1875,"grass":1404,"n":308},"ferna":{"all":1770,"hard":1807,"clay":1680,"grass":1515,"n":298},"prest":{"all":1648,"hard":1684,"clay":1352,"grass":1435,"n":251},"tauso":{"all":1865,"hard":1891,"clay":1712,"grass":1568,"n":286},"bartu":{"all":1829,"hard":1721,"clay":1771,"grass":1737,"n":247},"korpa":{"all":1660,"hard":1626,"clay":1709,"grass":1232,"n":295},"sheri":{"all":1727,"hard":1271,"clay":1785,"grass":1333,"n":297},"bejle":{"all":1782,"hard":1809,"clay":1783,"grass":1348,"n":252},"grabh":{"all":1605,"hard":1450,"clay":1656,"grass":1209,"n":294},"chara":{"all":1720,"hard":1589,"clay":1711,"grass":1616,"n":286},"eala":{"all":1925,"hard":1799,"clay":1600,"grass":1844,"n":299},"kasin":{"all":1582,"hard":1613,"clay":1557,"grass":1435,"n":294},"nosko":{"all":2070,"hard":1926,"clay":1726,"grass":1981,"n":290},"snigu":{"all":1851,"hard":1812,"clay":1639,"grass":1647,"n":292},"selek":{"all":1641,"hard":1684,"clay":1600,"grass":1515,"n":295},"shnai":{"all":1915,"hard":1849,"clay":1879,"grass":1638,"n":295},"sun":{"all":1646,"hard":1753,"clay":1474,"grass":1455,"n":291},"seide":{"all":1596,"hard":1651,"clay":1544,"grass":1457,"n":280},"walte":{"all":1686,"hard":1559,"clay":1749,"grass":1352,"n":303},"joint":{"all":1670,"hard":1698,"clay":1665,"grass":1608,"n":210},"udvar":{"all":1688,"hard":1567,"clay":1687,"grass":1502,"n":314},"krueg":{"all":1834,"hard":1728,"clay":1645,"grass":1728,"n":294},"bucsa":{"all":1776,"hard":1796,"clay":1501,"grass":1575,"n":302},"volyn1":{"all":1820,"hard":1716,"clay":1776,"grass":1663,"n":296},"rakhi":{"all":1688,"hard":1672,"clay":1637,"grass":1575,"n":296},"arang":{"all":1597,"hard":1577,"clay":1532,"grass":1454,"n":284},"timof":{"all":1760,"hard":1655,"clay":1791,"grass":1562,"n":286},"parry":{"all":1756,"hard":1613,"clay":1683,"grass":1665,"n":301},"marci":{"all":1724,"hard":1622,"clay":1730,"grass":1513,"n":268},"kraus":{"all":1724,"hard":1634,"clay":1756,"grass":1448,"n":296},"valen":{"all":1824,"hard":1851,"clay":1857,"grass":1512,"n":150},"ruzic":{"all":1726,"hard":1712,"clay":1600,"grass":1565,"n":293},"mboko":{"all":2052,"hard":2059,"clay":1848,"grass":1542,"n":210},"jacqu":{"all":1578,"hard":1590,"clay":1540,"grass":1523,"n":305},"erjav":{"all":1606,"hard":1493,"clay":1649,"grass":1456,"n":296},"sonme":{"all":1782,"hard":1704,"clay":1659,"grass":1631,"n":297},"uchij":{"all":1637,"hard":1642,"clay":1616,"grass":1328,"n":298},"korne":{"all":1733,"hard":1759,"clay":1637,"grass":1511,"n":175},"manei":{"all":1734,"hard":1658,"clay":1716,"grass":1647,"n":291},"semen":{"all":1588,"hard":1563,"clay":1650,"grass":1464,"n":292},"queve":{"all":1733,"hard":1641,"clay":1744,"grass":1462,"n":217},"kuder":{"all":1697,"hard":1661,"clay":1686,"grass":1546,"n":293},"gibso":{"all":1755,"hard":1822,"clay":1488,"grass":1500,"n":297},"andre":{"all":2108,"hard":2018,"clay":2103,"grass":1698,"n":240},"sierr":{"all":1798,"hard":1583,"clay":1826,"grass":1609,"n":293},"tagge":{"all":1720,"hard":1714,"clay":1712,"grass":1416,"n":122},"jovic":{"all":1984,"hard":1881,"clay":1797,"grass":1840,"n":153},"vande":{"all":1688,"hard":1785,"clay":1543,"grass":1469,"n":294}}